Metadata-Version: 2.1
Name: setfit-dont-use-deprecated-dataset-filter
Version: 1.1.0.dev0
Summary: Efficient few-shot learning with Sentence Transformers
Author-email: tayursky@gmail.com
License: Apache 2.0
Keywords: nlp,machine learning,fewshot learning,transformers
Classifier: Development Status :: 1 - Planning
Classifier: Intended Audience :: Developers
Classifier: Intended Audience :: Education
Classifier: Intended Audience :: Science/Research
Classifier: License :: OSI Approved :: Apache Software License
Classifier: Operating System :: OS Independent
Classifier: Programming Language :: Python :: 3
Classifier: Programming Language :: Python :: 3.8
Classifier: Programming Language :: Python :: 3.9
Classifier: Programming Language :: Python :: 3.10
Classifier: Topic :: Scientific/Engineering :: Artificial Intelligence
Provides-Extra: absa
Provides-Extra: codecarbon
Provides-Extra: compat_tests
Provides-Extra: dev
Provides-Extra: docs
Provides-Extra: onnx
Provides-Extra: openvino
Provides-Extra: optuna
Provides-Extra: quality
Provides-Extra: tests
License-File: LICENSE
